tttoneliner/__init__.py
tttoneliner/__main__.py
tttoneliner/tttoneliner.py
tttoneliner-0.0.1.dist-info/METADATA
tttoneliner-0.0.1.dist-info/WHEEL
tttoneliner-0.0.1.dist-info/entry_points.txt
tttoneliner-0.0.1.dist-info/top_level.txt
tttoneliner-0.0.1.dist-info/RECORD
