Metadata-Version: 2.4
Name: tttoneliner
Version: 0.0.1
Summary: The game of Tic-Tac-Toe in one line of code.
Author-email: alternyxx <alternyxx@gmail.com>
Maintainer-email: alternyxx <alternyxx@gmail.com>
Project-URL: repository, https://github.com/alternyxx/tttoneliner/
Requires-Python: >=3.10
